np_codeocean-0.3.5.dist-info/METADATA
np_codeocean-0.3.5.dist-info/WHEEL
np_codeocean-0.3.5.dist-info/entry_points.txt
np_codeocean/__init__.py
np_codeocean/metadata/__init__.py
np_codeocean/metadata/common.py
np_codeocean/metadata/core.py
np_codeocean/metadata/dynamic_routing_task_etl.py
np_codeocean/metadata/model_templates/__init__.py
np_codeocean/metadata/model_templates/behavior_box.py
np_codeocean/metadata/model_templates/neuropixels_rig.py
np_codeocean/metadata/np.py
np_codeocean/metadata/rigs.py
np_codeocean/metadata/storage.py
np_codeocean/metadata/update.py
np_codeocean/metadata/utils.py
np_codeocean/np_session_utils.py
np_codeocean/scripts/upload_dynamic_routing_behavior.py
np_codeocean/scripts/upload_dynamic_routing_ecephys.py
np_codeocean/scripts/upload_split_recordings_example.py
np_codeocean/utils.py
np_codeocean-0.3.5.dist-info/RECORD
