Metadata-Version: 2.1
Name: np_codeocean
Version: 0.3.5
Summary: Tools for uploading and interacting with Mindscope Neuropixels experiments on Code Ocean
Author-Email: Ben Hardcastle <ben.hardcastle@alleninstitute.org>, Chris Mochizuki <chrism@alleninstitute.org>, Arjun Sridhar <arjun.sridhar@alleninstitute.org>
License: MIT
Classifier: Programming Language :: Python :: 3
Classifier: Programming Language :: Python :: 3.9
Classifier: Programming Language :: Python :: 3.10
Classifier: Programming Language :: Python :: 3.11
Classifier: License :: OSI Approved :: MIT License
Classifier: Operating System :: Microsoft :: Windows
Classifier: Operating System :: POSIX :: Linux
Project-URL: Source, https://github.com/AllenInstitute/np_codeocean
Project-URL: Issues, https://github.com/AllenInstitute/np_codeocean/issues
Requires-Python: >=3.10
Requires-Dist: np_session>=0.6.44
Requires-Dist: np-tools>=0.1.23
Requires-Dist: np-config>=0.4.33
Requires-Dist: requests>=2.31.0
Requires-Dist: npc-session>=0.1.34
Requires-Dist: polars>=0.20.16
Requires-Dist: npc-lims>=0.1.168
Requires-Dist: npc-ephys>=0.1.32
Requires-Dist: wavpack-numcodecs<0.2
Requires-Dist: cryptography<43.0
Requires-Dist: aind-data-transfer-service>=1.15.0
Requires-Dist: aind-slurm-rest-v2==0.0.3
Requires-Dist: aind-codeocean-pipeline-monitor>=0.5.2
